toclo/__init__.py
toclo/__main__.py
toclo/cli.py
toclo/commands/__init__.py
toclo/commands/add.py
toclo/commands/base.py
toclo/commands/complete.py
toclo/commands/delete.py
toclo/commands/functions.py
toclo/commands/ls.py
toclo/commands/modify.py
toclo-1.1.25.dist-info/DESCRIPTION.rst
toclo-1.1.25.dist-info/METADATA
toclo-1.1.25.dist-info/RECORD
toclo-1.1.25.dist-info/WHEEL
toclo-1.1.25.dist-info/entry_points.txt
toclo-1.1.25.dist-info/metadata.json
toclo-1.1.25.dist-info/top_level.txt
