Metadata-Version: 2.0
Name: toclo
Version: 1.1.25
Summary: A todo list command line program in Python.
Home-page: https://github.com/Verssae/toclo
Author: Verssae
Author-email: sparky@hanynag.ac.kr
License: MIT
Download-URL: https://github.com/Verssae/toclo.git
Keywords: todolist
Platform: UNKNOWN
Classifier: Natural Language :: English
Classifier: Natural Language :: Korean
Classifier: Operating System :: OS Independent
Classifier: Programming Language :: Python 
Requires-Python: >= 3
Requires-Dist: colorama
Requires-Dist: docopt
